{
    "AX": {
        "error": 0.010438496152700757,
        "error_type": "SEM",
        "filter_outliers_dict": {
            "filter_outliers": true,
            "iterations": 1,
            "std_devs": 3,
            "use_iqr_filtering": false,
            "use_standard_deviation_filtering": false
        },
        "fit": "average",
        "fn": 30,
        "include_baseline_error": true,
        "n": 30,
        "outlier_excluded": [],
        "reviewed": true,
        "user_excluded": [],
        "value": 0.11131968622406324
    },
    "CDD": {
        "error": 2.429862518117463e-05,
        "error_type": "SEM",
        "filter_outliers_dict": {
            "filter_outliers": true,
            "iterations": 1,
            "std_devs": 10,
            "use_iqr_filtering": false,
            "use_standard_deviation_filtering": false
        },
        "fit": "average",
        "fn": 30,
        "include_baseline_error": true,
        "n": 30,
        "outlier_excluded": [],
        "reviewed": true,
        "user_excluded": [],
        "value": 0.00013406367264299964
    },
    "H1": {
        "error": 0.007419850521056966,
        "error_type": "SEM",
        "filter_outliers_dict": {
            "filter_outliers": true,
            "iterations": 1,
            "std_devs": 3,
            "use_iqr_filtering": false,
            "use_standard_deviation_filtering": false
        },
        "fit": "average",
        "fn": 30,
        "include_baseline_error": true,
        "n": 30,
        "outlier_excluded": [],
        "reviewed": true,
        "user_excluded": [],
        "value": 0.07104260730557144
    },
    "H2": {
        "error": 0.0590288692552601,
        "error_type": "SEM",
        "filter_outliers_dict": {
            "filter_outliers": true,
            "iterations": 1,
            "std_devs": 2
        },
        "fit": "average",
        "value": -0.42935488119402926
    },
    "L1": {
        "error": 0.004283402564004589,
        "error_type": "SEM",
        "filter_outliers_dict": {
            "filter_outliers": true,
            "iterations": 1,
            "std_devs": 3,
            "use_iqr_filtering": false,
            "use_standard_deviation_filtering": false
        },
        "fit": "average",
        "fn": 30,
        "include_baseline_error": true,
        "n": 30,
        "outlier_excluded": [],
        "reviewed": true,
        "user_excluded": [],
        "value": 0.03300636343192309
    },
    "L2": {
        "error": 0.005516681260600314,
        "error_type": "SEM",
        "filter_outliers_dict": {
            "filter_outliers": true,
            "iterations": 1,
            "std_devs": 3,
            "use_iqr_filtering": false,
            "use_standard_deviation_filtering": false
        },
        "fit": "average",
        "fn": 30,
        "include_baseline_error": true,
        "n": 30,
        "outlier_excluded": [],
        "reviewed": true,
        "user_excluded": [],
        "value": -0.03945948059360186
    }
}